c3loc/__init__.py
c3loc/_static_version.py
c3loc/_version.py
c3loc/config.py
c3loc/db.py
c3loc/db_next.py
c3loc/stats.py
c3loc/alembic/README
c3loc/alembic/env.py
c3loc/alembic/script.py.mako
c3loc/alembic/versions/#fa1582c9a701_adds_ssr_sla.py#
c3loc/alembic/versions/08158a1b9f0e_initial_schema.py
c3loc/alembic/versions/1100e9db1a0d_change_alertwet_default_name_to_hex_.py
c3loc/alembic/versions/168e8731e481_adds_history_schema.py
c3loc/alembic/versions/1a641c271945_add_macbeacon_mopeka.py
c3loc/alembic/versions/1a641c271945_add_macbeacon_mopeka.py~
c3loc/alembic/versions/44f605b1cfa0_modify_history_for_start_end.py
c3loc/alembic/versions/515df7865792_adds_gist_tsrange_index_to_history.py
c3loc/alembic/versions/5ccf897e51af_add_alarm.py
c3loc/alembic/versions/5eae6a0253f5_adds_zone_start_to_tags.py
c3loc/alembic/versions/6b0896f05118_adds_sensors_table.py
c3loc/alembic/versions/720d3e9a9af0_adds_alarm_active_field_to_tags.py
c3loc/alembic/versions/78e80c3339ff_add_alarm_priority.py
c3loc/alembic/versions/92eaed4a95e3_log_relation_unlogged.py
c3loc/alembic/versions/9581ffb09767_adds_settings_table_and_hysteresis.py
c3loc/alembic/versions/b06fbcb5e5d3_adds_alertwet_beacon_type.py
c3loc/alembic/versions/dbe74359375f_drop_uk_mac_constraint_from_tags_table.py
c3loc/alembic/versions/fa1582c9a701_adds_ssr_sla.py
c3loc/api/__init__.py
c3loc/api/alarms.py
c3loc/api/groups.py
c3loc/api/listeners.py
c3loc/api/main.py
c3loc/api/proximity.py
c3loc/api/schemas.py
c3loc/api/sensors.py
c3loc/api/server_meta.py
c3loc/api/tags.py
c3loc/api/views.py
c3loc/api/zones.py
c3loc/api2/__init__.py
c3loc/api2/alarms.py
c3loc/api2/dependencies.py
c3loc/api2/groups.py
c3loc/api2/listeners.py
c3loc/api2/main.py
c3loc/api2/proximity.py
c3loc/api2/queries.py
c3loc/api2/sensors.py
c3loc/api2/tags.py
c3loc/api2/zones.py
c3loc/api2/schemas/__init__.py
c3loc/api2/schemas/alarms.py
c3loc/api2/schemas/groups.py
c3loc/api2/schemas/listeners.py
c3loc/api2/schemas/proximity.py
c3loc-0.7.12.dist-info/METADATA
c3loc-0.7.12.dist-info/WHEEL
c3loc-0.7.12.dist-info/entry_points.txt
c3loc-0.7.12.dist-info/top_level.txt
c3loc-0.7.12.dist-info/RECORD
