Metadata-Version: 2.1
Name: c3loc
Version: 0.7.12
Summary: C3 Enhanced Proximity Location Services
Home-page: https://gitlab.com/C3Wireless/c3loc
Author: C3 Wireless
Author-email: support@c3wireless.com
License: MIT
Keywords: c3 c3wireless btle beacon ibeacon
Classifier: Development Status :: 4 - Beta
Classifier: Intended Audience :: Developers
Classifier: License :: OSI Approved :: MIT License
Classifier: Programming Language :: Python :: 3
Classifier: Programming Language :: Python :: 3.6
Classifier: Programming Language :: Python :: 3.7
Classifier: Programming Language :: Python :: 3.8
Requires-Dist: alembic
Requires-Dist: asyncpg
Requires-Dist: aiohttp
Requires-Dist: aiohttp-cors
Requires-Dist: aiohttp-jinja2
Requires-Dist: automat
Requires-Dist: click
Requires-Dist: marshmallow
Requires-Dist: protobuf
Requires-Dist: psycopg2
Requires-Dist: python-lzo
Requires-Dist: cryptography
Requires-Dist: python-dateutil
Requires-Dist: pytz
Requires-Dist: jinja2
Requires-Dist: sqlalchemy
Requires-Dist: sqlalchemy-utils
Requires-Dist: fastapi
Requires-Dist: pydantic
Requires-Dist: uvicorn
Provides-Extra: test
Requires-Dist: pytest ; extra == 'test'
Requires-Dist: pytest-cov ; extra == 'test'
Requires-Dist: pytest-asyncio ; extra == 'test'
Requires-Dist: hypothesis ; extra == 'test'
Requires-Dist: aiosqlite ; extra == 'test'
Requires-Dist: httpx ; extra == 'test'
Requires-Dist: mypy ; extra == 'test'
Requires-Dist: gevent ; extra == 'test'
Requires-Dist: coverage ; extra == 'test'
